py_spam_hunter_client/__init__.py
py_spam_hunter_client/async_spam_hunter_client.py
py_spam_hunter_client/client_utils.py
py_spam_hunter_client/sync_spam_hunter_client.py
py_spam_hunter_client/exceptions/__init__.py
py_spam_hunter_client/exceptions/check_exception.py
py_spam_hunter_client/messages/__init__.py
py_spam_hunter_client/messages/checked_message.py
py_spam_hunter_client/messages/message.py
py_spam_hunter_client-3.1.3.dist-info/licenses/LICENSE
py_spam_hunter_client-3.1.3.dist-info/METADATA
py_spam_hunter_client-3.1.3.dist-info/WHEEL
py_spam_hunter_client-3.1.3.dist-info/top_level.txt
py_spam_hunter_client-3.1.3.dist-info/RECORD
