Metadata-Version: 2.4
Name: py-spam-hunter-client
Version: 3.1.3
Summary: A client for SpamHunter API
Home-page: https://github.com/MakarMS/py-spam-hunter-client
Author: Makar
Author-email: makar.mikhalchenko@bk.ru
Classifier: Programming Language :: Python :: 3
Classifier: License :: OSI Approved :: MIT License
Classifier: Operating System :: OS Independent
Requires-Python: >=3.6
License-File: LICENSE
Requires-Dist: aiohttp
Requires-Dist: requests
Requires-Dist: langdetect
Dynamic: author
Dynamic: author-email
Dynamic: classifier
Dynamic: description
Dynamic: description-content-type
Dynamic: home-page
Dynamic: license-file
Dynamic: requires-dist
Dynamic: requires-python
Dynamic: summary
